datascience_gear/__init__.py
datascience_gear/exploration.py
datascience_gear-0.1.6.7.dist-info/WHEEL
datascience_gear-0.1.6.7.dist-info/METADATA
datascience_gear-0.1.6.7.dist-info/RECORD
