Metadata-Version: 2.1
Name: datascience-gear
Version: 0.1.6.7
Summary: 
Author: sinclairfr
Author-email: sixfoursuited@gmail.com
Requires-Python: >=3.7,<4.0
Classifier: Programming Language :: Python :: 3
Classifier: Programming Language :: Python :: 3.10
Classifier: Programming Language :: Python :: 3.7
Classifier: Programming Language :: Python :: 3.8
Classifier: Programming Language :: Python :: 3.9
Requires-Dist: matplotlib (>=3.5.1,<3.6.0)
Requires-Dist: numpy (>=1.22.0,<1.23.0)
Requires-Dist: pandas (>=1.3.5,<1.4.0)
Requires-Dist: scipy (>=1.7.3,<1.8.0)
Requires-Dist: seaborn (>=0.11.2,<0.12.0)
